{
  "data": [
    {
      "timestamp": 1722474000,
      "price": 76.85,
      "datetime": "2024-08-01 04:00"
    },
    {
      "timestamp": 1722477600,
      "price": 81.21,
      "datetime": "2024-08-01 05:00"
    },
    {
      "timestamp": 1722481200,
      "price": 101.63,
      "datetime": "2024-08-01 06:00"
    },
    {
      "timestamp": 1722484800,
      "price": 126.67,
      "datetime": "2024-08-01 07:00"
    },
    {
      "timestamp": 1722488400,
      "price": 145.05,
      "datetime": "2024-08-01 08:00"
    },
    {
      "timestamp": 1722492000,
      "price": 145.02,
      "datetime": "2024-08-01 09:00"
    },
    {
      "timestamp": 1722495600,
      "price": 170.06,
      "datetime": "2024-08-01 10:00"
    },
    {
      "timestamp": 1722499200,
      "price": 102.58,
      "datetime": "2024-08-01 11:00"
    },
    {
      "timestamp": 1722502800,
      "price": 57.1,
      "datetime": "2024-08-01 12:00"
    },
    {
      "timestamp": 1722506400,
      "price": 77.72,
      "datetime": "2024-08-01 13:00"
    },
    {
      "timestamp": 1722510000,
      "price": 58.43,
      "datetime": "2024-08-01 14:00"
    },
    {
      "timestamp": 1722513600,
      "price": 77.75,
      "datetime": "2024-08-01 15:00"
    },
    {
      "timestamp": 1722517200,
      "price": 64.02,
      "datetime": "2024-08-01 16:00"
    },
    {
      "timestamp": 1722520800,
      "price": 116.91,
      "datetime": "2024-08-01 17:00"
    },
    {
      "timestamp": 1722524400,
      "price": 88.37,
      "datetime": "2024-08-01 18:00"
    },
    {
      "timestamp": 1722528000,
      "price": 107.0,
      "datetime": "2024-08-01 19:00"
    },
    {
      "timestamp": 1722531600,
      "price": 149.03,
      "datetime": "2024-08-01 20:00"
    },
    {
      "timestamp": 1722535200,
      "price": 189.99,
      "datetime": "2024-08-01 21:00"
    },
    {
      "timestamp": 1722538800,
      "price": 121.05,
      "datetime": "2024-08-01 22:00"
    },
    {
      "timestamp": 1722542400,
      "price": 124.91,
      "datetime": "2024-08-01 23:00"
    },
    {
      "timestamp": 1722546000,
      "price": 103.99,
      "datetime": "2024-08-02 00:00"
    },
    {
      "timestamp": 1722549600,
      "price": 93.93,
      "datetime": "2024-08-02 01:00"
    },
    {
      "timestamp": 1722553200,
      "price": 88.93,
      "datetime": "2024-08-02 02:00"
    },
    {
      "timestamp": 1722556800,
      "price": 86.59,
      "datetime": "2024-08-02 03:00"
    },
    {
      "timestamp": 1722560400,
      "price": 74.86,
      "datetime": "2024-08-02 04:00"
    },
    {
      "timestamp": 1722564000,
      "price": 79.18,
      "datetime": "2024-08-02 05:00"
    },
    {
      "timestamp": 1722567600,
      "price": 90.25,
      "datetime": "2024-08-02 06:00"
    },
    {
      "timestamp": 1722571200,
      "price": 110.9,
      "datetime": "2024-08-02 07:00"
    },
    {
      "timestamp": 1722574800,
      "price": 300.05,
      "datetime": "2024-08-02 08:00"
    },
    {
      "timestamp": 1722578400,
      "price": 300.0,
      "datetime": "2024-08-02 09:00"
    },
    {
      "timestamp": 1722582000,
      "price": 199.01,
      "datetime": "2024-08-02 10:00"
    },
    {
      "timestamp": 1722585600,
      "price": 132.32,
      "datetime": "2024-08-02 11:00"
    },
    {
      "timestamp": 1722589200,
      "price": 75.82,
      "datetime": "2024-08-02 12:00"
    },
    {
      "timestamp": 1722592800,
      "price": 71.81,
      "datetime": "2024-08-02 13:00"
    },
    {
      "timestamp": 1722596400,
      "price": 64.1,
      "datetime": "2024-08-02 14:00"
    },
    {
      "timestamp": 1722600000,
      "price": 64.09,
      "datetime": "2024-08-02 15:00"
    },
    {
      "timestamp": 1722603600,
      "price": 126.92,
      "datetime": "2024-08-02 16:00"
    },
    {
      "timestamp": 1722607200,
      "price": 291.32,
      "datetime": "2024-08-02 17:00"
    },
    {
      "timestamp": 1722610800,
      "price": 114.2,
      "datetime": "2024-08-02 18:00"
    },
    {
      "timestamp": 1722614400,
      "price": 128.11,
      "datetime": "2024-08-02 19:00"
    },
    {
      "timestamp": 1722618000,
      "price": 317.5,
      "datetime": "2024-08-02 20:00"
    },
    {
      "timestamp": 1722621600,
      "price": 325.07,
      "datetime": "2024-08-02 21:00"
    },
    {
      "timestamp": 1722625200,
      "price": 300.01,
      "datetime": "2024-08-02 22:00"
    },
    {
      "timestamp": 1722628800,
      "price": 115.28,
      "datetime": "2024-08-02 23:00"
    },
    {
      "timestamp": 1722632400,
      "price": 123.06,
      "datetime": "2024-08-03 00:00"
    },
    {
      "timestamp": 1722636000,
      "price": 177.91,
      "datetime": "2024-08-03 01:00"
    },
    {
      "timestamp": 1722639600,
      "price": 250.0,
      "datetime": "2024-08-03 02:00"
    },
    {
      "timestamp": 1722643200,
      "price": 118.95,
      "datetime": "2024-08-03 03:00"
    },
    {
      "timestamp": 1722646800,
      "price": 87.83,
      "datetime": "2024-08-03 04:00"
    },
    {
      "timestamp": 1722650400,
      "price": 85.05,
      "datetime": "2024-08-03 05:00"
    },
    {
      "timestamp": 1722654000,
      "price": 93.54,
      "datetime": "2024-08-03 06:00"
    },
    {
      "timestamp": 1722657600,
      "price": 101.64,
      "datetime": "2024-08-03 07:00"
    },
    {
      "timestamp": 1722661200,
      "price": 93.64,
      "datetime": "2024-08-03 08:00"
    },
    {
      "timestamp": 1722664800,
      "price": 82.95,
      "datetime": "2024-08-03 09:00"
    },
    {
      "timestamp": 1722668400,
      "price": 64.82,
      "datetime": "2024-08-03 10:00"
    },
    {
      "timestamp": 1722672000,
      "price": 32.44,
      "datetime": "2024-08-03 11:00"
    },
    {
      "timestamp": 1722675600,
      "price": 20.36,
      "datetime": "2024-08-03 12:00"
    },
    {
      "timestamp": 1722679200,
      "price": 14.66,
      "datetime": "2024-08-03 13:00"
    },
    {
      "timestamp": 1722682800,
      "price": 6.41,
      "datetime": "2024-08-03 14:00"
    },
    {
      "timestamp": 1722686400,
      "price": 50.0,
      "datetime": "2024-08-03 15:00"
    },
    {
      "timestamp": 1722690000,
      "price": 75.02,
      "datetime": "2024-08-03 16:00"
    },
    {
      "timestamp": 1722693600,
      "price": 50.0,
      "datetime": "2024-08-03 17:00"
    },
    {
      "timestamp": 1722697200,
      "price": 65.08,
      "datetime": "2024-08-03 18:00"
    },
    {
      "timestamp": 1722700800,
      "price": 250.08,
      "datetime": "2024-08-03 19:00"
    },
    {
      "timestamp": 1722704400,
      "price": 145.1,
      "datetime": "2024-08-03 20:00"
    },
    {
      "timestamp": 1722708000,
      "price": 165.08,
      "datetime": "2024-08-03 21:00"
    },
    {
      "timestamp": 1722711600,
      "price": 129.08,
      "datetime": "2024-08-03 22:00"
    },
    {
      "timestamp": 1722715200,
      "price": 129.0,
      "datetime": "2024-08-03 23:00"
    },
    {
      "timestamp": 1722718800,
      "price": 127.99,
      "datetime": "2024-08-04 00:00"
    },
    {
      "timestamp": 1722722400,
      "price": 130.06,
      "datetime": "2024-08-04 01:00"
    },
    {
      "timestamp": 1722726000,
      "price": 130.01,
      "datetime": "2024-08-04 02:00"
    },
    {
      "timestamp": 1722729600,
      "price": 111.31,
      "datetime": "2024-08-04 03:00"
    },
    {
      "timestamp": 1722733200,
      "price": 91.11,
      "datetime": "2024-08-04 04:00"
    },
    {
      "timestamp": 1722736800,
      "price": 88.63,
      "datetime": "2024-08-04 05:00"
    },
    {
      "timestamp": 1722740400,
      "price": 81.69,
      "datetime": "2024-08-04 06:00"
    },
    {
      "timestamp": 1722744000,
      "price": 76.11,
      "datetime": "2024-08-04 07:00"
    },
    {
      "timestamp": 1722747600,
      "price": 71.73,
      "datetime": "2024-08-04 08:00"
    },
    {
      "timestamp": 1722751200,
      "price": 64.43,
      "datetime": "2024-08-04 09:00"
    },
    {
      "timestamp": 1722754800,
      "price": 28.33,
      "datetime": "2024-08-04 10:00"
    },
    {
      "timestamp": 1722758400,
      "price": 122.75,
      "datetime": "2024-08-04 11:00"
    },
    {
      "timestamp": 1722762000,
      "price": 5.0,
      "datetime": "2024-08-04 12:00"
    },
    {
      "timestamp": 1722765600,
      "price": 100.05,
      "datetime": "2024-08-04 13:00"
    },
    {
      "timestamp": 1722769200,
      "price": 90.5,
      "datetime": "2024-08-04 14:00"
    },
    {
      "timestamp": 1722772800,
      "price": 5.0,
      "datetime": "2024-08-04 15:00"
    },
    {
      "timestamp": 1722776400,
      "price": 4.99,
      "datetime": "2024-08-04 16:00"
    },
    {
      "timestamp": 1722780000,
      "price": 80.05,
      "datetime": "2024-08-04 17:00"
    },
    {
      "timestamp": 1722783600,
      "price": 123.57,
      "datetime": "2024-08-04 18:00"
    },
    {
      "timestamp": 1722787200,
      "price": 185.09,
      "datetime": "2024-08-04 19:00"
    },
    {
      "timestamp": 1722790800,
      "price": 145.74,
      "datetime": "2024-08-04 20:00"
    },
    {
      "timestamp": 1722794400,
      "price": 178.06,
      "datetime": "2024-08-04 21:00"
    },
    {
      "timestamp": 1722798000,
      "price": 130.05,
      "datetime": "2024-08-04 22:00"
    },
    {
      "timestamp": 1722801600,
      "price": 118.9,
      "datetime": "2024-08-04 23:00"
    },
    {
      "timestamp": 1722805200,
      "price": 185.01,
      "datetime": "2024-08-05 00:00"
    },
    {
      "timestamp": 1722808800,
      "price": 165.01,
      "datetime": "2024-08-05 01:00"
    },
    {
      "timestamp": 1722812400,
      "price": 104.49,
      "datetime": "2024-08-05 02:00"
    },
    {
      "timestamp": 1722816000,
      "price": 82.59,
      "datetime": "2024-08-05 03:00"
    },
    {
      "timestamp": 1722819600,
      "price": 86.23,
      "datetime": "2024-08-05 04:00"
    },
    {
      "timestamp": 1722823200,
      "price": 118.9,
      "datetime": "2024-08-05 05:00"
    },
    {
      "timestamp": 1722826800,
      "price": 150.09,
      "datetime": "2024-08-05 06:00"
    },
    {
      "timestamp": 1722830400,
      "price": 168.56,
      "datetime": "2024-08-05 07:00"
    },
    {
      "timestamp": 1722834000,
      "price": 195.06,
      "datetime": "2024-08-05 08:00"
    },
    {
      "timestamp": 1722837600,
      "price": 165.04,
      "datetime": "2024-08-05 09:00"
    },
    {
      "timestamp": 1722841200,
      "price": 150.1,
      "datetime": "2024-08-05 10:00"
    },
    {
      "timestamp": 1722844800,
      "price": 126.5,
      "datetime": "2024-08-05 11:00"
    },
    {
      "timestamp": 1722848400,
      "price": 79.42,
      "datetime": "2024-08-05 12:00"
    },
    {
      "timestamp": 1722852000,
      "price": 73.09,
      "datetime": "2024-08-05 13:00"
    },
    {
      "timestamp": 1722855600,
      "price": 42.05,
      "datetime": "2024-08-05 14:00"
    },
    {
      "timestamp": 1722859200,
      "price": 50.0,
      "datetime": "2024-08-05 15:00"
    },
    {
      "timestamp": 1722862800,
      "price": 118.92,
      "datetime": "2024-08-05 16:00"
    },
    {
      "timestamp": 1722866400,
      "price": 118.94,
      "datetime": "2024-08-05 17:00"
    },
    {
      "timestamp": 1722870000,
      "price": 96.22,
      "datetime": "2024-08-05 18:00"
    },
    {
      "timestamp": 1722873600,
      "price": 116.74,
      "datetime": "2024-08-05 19:00"
    },
    {
      "timestamp": 1722877200,
      "price": 165.01,
      "datetime": "2024-08-05 20:00"
    },
    {
      "timestamp": 1722880800,
      "price": 276.71,
      "datetime": "2024-08-05 21:00"
    },
    {
      "timestamp": 1722884400,
      "price": 187.62,
      "datetime": "2024-08-05 22:00"
    },
    {
      "timestamp": 1722888000,
      "price": 128.74,
      "datetime": "2024-08-05 23:00"
    },
    {
      "timestamp": 1722891600,
      "price": 107.49,
      "datetime": "2024-08-06 00:00"
    },
    {
      "timestamp": 1722895200,
      "price": 105.82,
      "datetime": "2024-08-06 01:00"
    },
    {
      "timestamp": 1722898800,
      "price": 98.86,
      "datetime": "2024-08-06 02:00"
    },
    {
      "timestamp": 1722902400,
      "price": 92.43,
      "datetime": "2024-08-06 03:00"
    },
    {
      "timestamp": 1722906000,
      "price": 88.71,
      "datetime": "2024-08-06 04:00"
    },
    {
      "timestamp": 1722909600,
      "price": 89.45,
      "datetime": "2024-08-06 05:00"
    },
    {
      "timestamp": 1722913200,
      "price": 99.48,
      "datetime": "2024-08-06 06:00"
    },
    {
      "timestamp": 1722916800,
      "price": 130.09,
      "datetime": "2024-08-06 07:00"
    },
    {
      "timestamp": 1722920400,
      "price": 170.07,
      "datetime": "2024-08-06 08:00"
    },
    {
      "timestamp": 1722924000,
      "price": 115.97,
      "datetime": "2024-08-06 09:00"
    },
    {
      "timestamp": 1722927600,
      "price": 75.36,
      "datetime": "2024-08-06 10:00"
    },
    {
      "timestamp": 1722931200,
      "price": 35.22,
      "datetime": "2024-08-06 11:00"
    },
    {
      "timestamp": 1722934800,
      "price": 22.75,
      "datetime": "2024-08-06 12:00"
    },
    {
      "timestamp": 1722938400,
      "price": 17.47,
      "datetime": "2024-08-06 13:00"
    },
    {
      "timestamp": 1722942000,
      "price": 16.33,
      "datetime": "2024-08-06 14:00"
    },
    {
      "timestamp": 1722945600,
      "price": 30.25,
      "datetime": "2024-08-06 15:00"
    },
    {
      "timestamp": 1722949200,
      "price": 19.92,
      "datetime": "2024-08-06 16:00"
    },
    {
      "timestamp": 1722952800,
      "price": 41.57,
      "datetime": "2024-08-06 17:00"
    },
    {
      "timestamp": 1722956400,
      "price": 82.18,
      "datetime": "2024-08-06 18:00"
    },
    {
      "timestamp": 1722960000,
      "price": 127.25,
      "datetime": "2024-08-06 19:00"
    },
    {
      "timestamp": 1722963600,
      "price": 176.8,
      "datetime": "2024-08-06 20:00"
    },
    {
      "timestamp": 1722967200,
      "price": 234.64,
      "datetime": "2024-08-06 21:00"
    },
    {
      "timestamp": 1722970800,
      "price": 173.18,
      "datetime": "2024-08-06 22:00"
    },
    {
      "timestamp": 1722974400,
      "price": 124.77,
      "datetime": "2024-08-06 23:00"
    },
    {
      "timestamp": 1722978000,
      "price": 101.48,
      "datetime": "2024-08-07 00:00"
    },
    {
      "timestamp": 1722981600,
      "price": 93.81,
      "datetime": "2024-08-07 01:00"
    },
    {
      "timestamp": 1722985200,
      "price": 85.86,
      "datetime": "2024-08-07 02:00"
    },
    {
      "timestamp": 1722988800,
      "price": 81.98,
      "datetime": "2024-08-07 03:00"
    },
    {
      "timestamp": 1722992400,
      "price": 86.89,
      "datetime": "2024-08-07 04:00"
    },
    {
      "timestamp": 1722996000,
      "price": 90.25,
      "datetime": "2024-08-07 05:00"
    },
    {
      "timestamp": 1722999600,
      "price": 109.1,
      "datetime": "2024-08-07 06:00"
    },
    {
      "timestamp": 1723003200,
      "price": 262.36,
      "datetime": "2024-08-07 07:00"
    },
    {
      "timestamp": 1723006800,
      "price": 343.3,
      "datetime": "2024-08-07 08:00"
    },
    {
      "timestamp": 1723010400,
      "price": 112.97,
      "datetime": "2024-08-07 09:00"
    },
    {
      "timestamp": 1723014000,
      "price": 91.87,
      "datetime": "2024-08-07 10:00"
    },
    {
      "timestamp": 1723017600,
      "price": 75.86,
      "datetime": "2024-08-07 11:00"
    },
    {
      "timestamp": 1723021200,
      "price": 64.59,
      "datetime": "2024-08-07 12:00"
    },
    {
      "timestamp": 1723024800,
      "price": 43.31,
      "datetime": "2024-08-07 13:00"
    },
    {
      "timestamp": 1723028400,
      "price": 35.33,
      "datetime": "2024-08-07 14:00"
    },
    {
      "timestamp": 1723032000,
      "price": 51.74,
      "datetime": "2024-08-07 15:00"
    },
    {
      "timestamp": 1723035600,
      "price": 69.85,
      "datetime": "2024-08-07 16:00"
    },
    {
      "timestamp": 1723039200,
      "price": 85.25,
      "datetime": "2024-08-07 17:00"
    },
    {
      "timestamp": 1723042800,
      "price": 116.85,
      "datetime": "2024-08-07 18:00"
    },
    {
      "timestamp": 1723046400,
      "price": 300.06,
      "datetime": "2024-08-07 19:00"
    },
    {
      "timestamp": 1723050000,
      "price": 172.04,
      "datetime": "2024-08-07 20:00"
    },
    {
      "timestamp": 1723053600,
      "price": 207.9,
      "datetime": "2024-08-07 21:00"
    },
    {
      "timestamp": 1723057200,
      "price": 164.19,
      "datetime": "2024-08-07 22:00"
    },
    {
      "timestamp": 1723060800,
      "price": 130.66,
      "datetime": "2024-08-07 23:00"
    },
    {
      "timestamp": 1723064400,
      "price": 106.19,
      "datetime": "2024-08-08 00:00"
    },
    {
      "timestamp": 1723068000,
      "price": 99.6,
      "datetime": "2024-08-08 01:00"
    },
    {
      "timestamp": 1723071600,
      "price": 89.82,
      "datetime": "2024-08-08 02:00"
    },
    {
      "timestamp": 1723075200,
      "price": 90.09,
      "datetime": "2024-08-08 03:00"
    },
    {
      "timestamp": 1723078800,
      "price": 90.93,
      "datetime": "2024-08-08 04:00"
    },
    {
      "timestamp": 1723082400,
      "price": 91.25,
      "datetime": "2024-08-08 05:00"
    },
    {
      "timestamp": 1723086000,
      "price": 125.12,
      "datetime": "2024-08-08 06:00"
    },
    {
      "timestamp": 1723089600,
      "price": 181.8,
      "datetime": "2024-08-08 07:00"
    },
    {
      "timestamp": 1723093200,
      "price": 196.67,
      "datetime": "2024-08-08 08:00"
    },
    {
      "timestamp": 1723096800,
      "price": 118.02,
      "datetime": "2024-08-08 09:00"
    },
    {
      "timestamp": 1723100400,
      "price": 110.5,
      "datetime": "2024-08-08 10:00"
    },
    {
      "timestamp": 1723104000,
      "price": 90.21,
      "datetime": "2024-08-08 11:00"
    },
    {
      "timestamp": 1723107600,
      "price": 74.71,
      "datetime": "2024-08-08 12:00"
    },
    {
      "timestamp": 1723111200,
      "price": 58.59,
      "datetime": "2024-08-08 13:00"
    },
    {
      "timestamp": 1723114800,
      "price": 54.44,
      "datetime": "2024-08-08 14:00"
    },
    {
      "timestamp": 1723118400,
      "price": 52.66,
      "datetime": "2024-08-08 15:00"
    },
    {
      "timestamp": 1723122000,
      "price": 110.12,
      "datetime": "2024-08-08 16:00"
    },
    {
      "timestamp": 1723125600,
      "price": 81.7,
      "datetime": "2024-08-08 17:00"
    },
    {
      "timestamp": 1723129200,
      "price": 115.0,
      "datetime": "2024-08-08 18:00"
    },
    {
      "timestamp": 1723132800,
      "price": 171.1,
      "datetime": "2024-08-08 19:00"
    },
    {
      "timestamp": 1723136400,
      "price": 146.76,
      "datetime": "2024-08-08 20:00"
    },
    {
      "timestamp": 1723140000,
      "price": 203.01,
      "datetime": "2024-08-08 21:00"
    },
    {
      "timestamp": 1723143600,
      "price": 140.92,
      "datetime": "2024-08-08 22:00"
    },
    {
      "timestamp": 1723147200,
      "price": 112.17,
      "datetime": "2024-08-08 23:00"
    },
    {
      "timestamp": 1723150800,
      "price": 94.93,
      "datetime": "2024-08-09 00:00"
    },
    {
      "timestamp": 1723154400,
      "price": 187.69,
      "datetime": "2024-08-09 01:00"
    },
    {
      "timestamp": 1723158000,
      "price": 86.31,
      "datetime": "2024-08-09 02:00"
    },
    {
      "timestamp": 1723161600,
      "price": 70.57,
      "datetime": "2024-08-09 03:00"
    },
    {
      "timestamp": 1723165200,
      "price": 75.09,
      "datetime": "2024-08-09 04:00"
    },
    {
      "timestamp": 1723168800,
      "price": 89.59,
      "datetime": "2024-08-09 05:00"
    },
    {
      "timestamp": 1723172400,
      "price": 95.93,
      "datetime": "2024-08-09 06:00"
    },
    {
      "timestamp": 1723176000,
      "price": 191.88,
      "datetime": "2024-08-09 07:00"
    },
    {
      "timestamp": 1723179600,
      "price": 250.05,
      "datetime": "2024-08-09 08:00"
    },
    {
      "timestamp": 1723183200,
      "price": 80.76,
      "datetime": "2024-08-09 09:00"
    },
    {
      "timestamp": 1723186800,
      "price": 50.0,
      "datetime": "2024-08-09 10:00"
    },
    {
      "timestamp": 1723190400,
      "price": 11.94,
      "datetime": "2024-08-09 11:00"
    },
    {
      "timestamp": 1723194000,
      "price": 25.05,
      "datetime": "2024-08-09 12:00"
    },
    {
      "timestamp": 1723197600,
      "price": 38.44,
      "datetime": "2024-08-09 13:00"
    },
    {
      "timestamp": 1723201200,
      "price": 7.47,
      "datetime": "2024-08-09 14:00"
    },
    {
      "timestamp": 1723204800,
      "price": 61.72,
      "datetime": "2024-08-09 15:00"
    },
    {
      "timestamp": 1723208400,
      "price": 55.85,
      "datetime": "2024-08-09 16:00"
    },
    {
      "timestamp": 1723212000,
      "price": 91.52,
      "datetime": "2024-08-09 17:00"
    },
    {
      "timestamp": 1723215600,
      "price": 134.67,
      "datetime": "2024-08-09 18:00"
    },
    {
      "timestamp": 1723219200,
      "price": 213.84,
      "datetime": "2024-08-09 19:00"
    },
    {
      "timestamp": 1723222800,
      "price": 141.22,
      "datetime": "2024-08-09 20:00"
    },
    {
      "timestamp": 1723226400,
      "price": 145.62,
      "datetime": "2024-08-09 21:00"
    },
    {
      "timestamp": 1723230000,
      "price": 135.56,
      "datetime": "2024-08-09 22:00"
    },
    {
      "timestamp": 1723233600,
      "price": 111.55,
      "datetime": "2024-08-09 23:00"
    },
    {
      "timestamp": 1723237200,
      "price": 90.03,
      "datetime": "2024-08-10 00:00"
    },
    {
      "timestamp": 1723240800,
      "price": 73.77,
      "datetime": "2024-08-10 01:00"
    },
    {
      "timestamp": 1723244400,
      "price": 91.34,
      "datetime": "2024-08-10 02:00"
    },
    {
      "timestamp": 1723248000,
      "price": 90.32,
      "datetime": "2024-08-10 03:00"
    },
    {
      "timestamp": 1723251600,
      "price": 88.26,
      "datetime": "2024-08-10 04:00"
    },
    {
      "timestamp": 1723255200,
      "price": 88.17,
      "datetime": "2024-08-10 05:00"
    },
    {
      "timestamp": 1723258800,
      "price": 90.88,
      "datetime": "2024-08-10 06:00"
    },
    {
      "timestamp": 1723262400,
      "price": 93.18,
      "datetime": "2024-08-10 07:00"
    },
    {
      "timestamp": 1723266000,
      "price": 79.51,
      "datetime": "2024-08-10 08:00"
    },
    {
      "timestamp": 1723269600,
      "price": 32.09,
      "datetime": "2024-08-10 09:00"
    },
    {
      "timestamp": 1723273200,
      "price": -0.28,
      "datetime": "2024-08-10 10:00"
    },
    {
      "timestamp": 1723276800,
      "price": -3.0,
      "datetime": "2024-08-10 11:00"
    },
    {
      "timestamp": 1723280400,
      "price": -10.0,
      "datetime": "2024-08-10 12:00"
    },
    {
      "timestamp": 1723284000,
      "price": -10.01,
      "datetime": "2024-08-10 13:00"
    },
    {
      "timestamp": 1723287600,
      "price": -10.0,
      "datetime": "2024-08-10 14:00"
    },
    {
      "timestamp": 1723291200,
      "price": -9.92,
      "datetime": "2024-08-10 15:00"
    },
    {
      "timestamp": 1723294800,
      "price": -10.01,
      "datetime": "2024-08-10 16:00"
    },
    {
      "timestamp": 1723298400,
      "price": -6.09,
      "datetime": "2024-08-10 17:00"
    },
    {
      "timestamp": 1723302000,
      "price": 0.0,
      "datetime": "2024-08-10 18:00"
    },
    {
      "timestamp": 1723305600,
      "price": 35.17,
      "datetime": "2024-08-10 19:00"
    },
    {
      "timestamp": 1723309200,
      "price": 114.41,
      "datetime": "2024-08-10 20:00"
    },
    {
      "timestamp": 1723312800,
      "price": 139.0,
      "datetime": "2024-08-10 21:00"
    },
    {
      "timestamp": 1723316400,
      "price": 131.29,
      "datetime": "2024-08-10 22:00"
    },
    {
      "timestamp": 1723320000,
      "price": 121.86,
      "datetime": "2024-08-10 23:00"
    },
    {
      "timestamp": 1723323600,
      "price": 100.06,
      "datetime": "2024-08-11 00:00"
    },
    {
      "timestamp": 1723327200,
      "price": 110.93,
      "datetime": "2024-08-11 01:00"
    },
    {
      "timestamp": 1723330800,
      "price": 108.08,
      "datetime": "2024-08-11 02:00"
    },
    {
      "timestamp": 1723334400,
      "price": 102.99,
      "datetime": "2024-08-11 03:00"
    },
    {
      "timestamp": 1723338000,
      "price": 87.28,
      "datetime": "2024-08-11 04:00"
    },
    {
      "timestamp": 1723341600,
      "price": 101.16,
      "datetime": "2024-08-11 05:00"
    },
    {
      "timestamp": 1723345200,
      "price": 4.1,
      "datetime": "2024-08-11 06:00"
    },
    {
      "timestamp": 1723348800,
      "price": -0.01,
      "datetime": "2024-08-11 07:00"
    },
    {
      "timestamp": 1723352400,
      "price": 73.5,
      "datetime": "2024-08-11 08:00"
    },
    {
      "timestamp": 1723356000,
      "price": 27.72,
      "datetime": "2024-08-11 09:00"
    },
    {
      "timestamp": 1723359600,
      "price": 0.0,
      "datetime": "2024-08-11 10:00"
    },
    {
      "timestamp": 1723363200,
      "price": -5.0,
      "datetime": "2024-08-11 11:00"
    },
    {
      "timestamp": 1723366800,
      "price": -6.09,
      "datetime": "2024-08-11 12:00"
    },
    {
      "timestamp": 1723370400,
      "price": -6.09,
      "datetime": "2024-08-11 13:00"
    },
    {
      "timestamp": 1723374000,
      "price": -7.01,
      "datetime": "2024-08-11 14:00"
    },
    {
      "timestamp": 1723377600,
      "price": -5.51,
      "datetime": "2024-08-11 15:00"
    },
    {
      "timestamp": 1723381200,
      "price": -7.01,
      "datetime": "2024-08-11 16:00"
    },
    {
      "timestamp": 1723384800,
      "price": -4.31,
      "datetime": "2024-08-11 17:00"
    },
    {
      "timestamp": 1723388400,
      "price": 0.01,
      "datetime": "2024-08-11 18:00"
    },
    {
      "timestamp": 1723392000,
      "price": 81.84,
      "datetime": "2024-08-11 19:00"
    },
    {
      "timestamp": 1723395600,
      "price": 121.14,
      "datetime": "2024-08-11 20:00"
    },
    {
      "timestamp": 1723399200,
      "price": 131.88,
      "datetime": "2024-08-11 21:00"
    },
    {
      "timestamp": 1723402800,
      "price": 124.24,
      "datetime": "2024-08-11 22:00"
    },
    {
      "timestamp": 1723406400,
      "price": 111.54,
      "datetime": "2024-08-11 23:00"
    },
    {
      "timestamp": 1723410000,
      "price": 98.23,
      "datetime": "2024-08-12 00:00"
    },
    {
      "timestamp": 1723413600,
      "price": 104.41,
      "datetime": "2024-08-12 01:00"
    },
    {
      "timestamp": 1723417200,
      "price": 94.37,
      "datetime": "2024-08-12 02:00"
    },
    {
      "timestamp": 1723420800,
      "price": 85.3,
      "datetime": "2024-08-12 03:00"
    },
    {
      "timestamp": 1723424400,
      "price": 87.57,
      "datetime": "2024-08-12 04:00"
    },
    {
      "timestamp": 1723428000,
      "price": 93.47,
      "datetime": "2024-08-12 05:00"
    },
    {
      "timestamp": 1723431600,
      "price": 115.1,
      "datetime": "2024-08-12 06:00"
    },
    {
      "timestamp": 1723435200,
      "price": 149.05,
      "datetime": "2024-08-12 07:00"
    },
    {
      "timestamp": 1723438800,
      "price": 142.23,
      "datetime": "2024-08-12 08:00"
    },
    {
      "timestamp": 1723442400,
      "price": 112.22,
      "datetime": "2024-08-12 09:00"
    },
    {
      "timestamp": 1723446000,
      "price": 70.75,
      "datetime": "2024-08-12 10:00"
    },
    {
      "timestamp": 1723449600,
      "price": 40.12,
      "datetime": "2024-08-12 11:00"
    },
    {
      "timestamp": 1723453200,
      "price": 16.04,
      "datetime": "2024-08-12 12:00"
    },
    {
      "timestamp": 1723456800,
      "price": 10.06,
      "datetime": "2024-08-12 13:00"
    },
    {
      "timestamp": 1723460400,
      "price": 6.98,
      "datetime": "2024-08-12 14:00"
    },
    {
      "timestamp": 1723464000,
      "price": 13.47,
      "datetime": "2024-08-12 15:00"
    },
    {
      "timestamp": 1723467600,
      "price": 14.76,
      "datetime": "2024-08-12 16:00"
    },
    {
      "timestamp": 1723471200,
      "price": 69.24,
      "datetime": "2024-08-12 17:00"
    },
    {
      "timestamp": 1723474800,
      "price": 91.0,
      "datetime": "2024-08-12 18:00"
    },
    {
      "timestamp": 1723478400,
      "price": 142.57,
      "datetime": "2024-08-12 19:00"
    },
    {
      "timestamp": 1723482000,
      "price": 203.0,
      "datetime": "2024-08-12 20:00"
    },
    {
      "timestamp": 1723485600,
      "price": 225.74,
      "datetime": "2024-08-12 21:00"
    },
    {
      "timestamp": 1723489200,
      "price": 136.06,
      "datetime": "2024-08-12 22:00"
    },
    {
      "timestamp": 1723492800,
      "price": 124.11,
      "datetime": "2024-08-12 23:00"
    },
    {
      "timestamp": 1723496400,
      "price": 102.75,
      "datetime": "2024-08-13 00:00"
    },
    {
      "timestamp": 1723500000,
      "price": 112.31,
      "datetime": "2024-08-13 01:00"
    },
    {
      "timestamp": 1723503600,
      "price": 97.02,
      "datetime": "2024-08-13 02:00"
    },
    {
      "timestamp": 1723507200,
      "price": 90.55,
      "datetime": "2024-08-13 03:00"
    },
    {
      "timestamp": 1723510800,
      "price": 87.05,
      "datetime": "2024-08-13 04:00"
    },
    {
      "timestamp": 1723514400,
      "price": 91.02,
      "datetime": "2024-08-13 05:00"
    },
    {
      "timestamp": 1723518000,
      "price": 97.99,
      "datetime": "2024-08-13 06:00"
    },
    {
      "timestamp": 1723521600,
      "price": 132.87,
      "datetime": "2024-08-13 07:00"
    },
    {
      "timestamp": 1723525200,
      "price": 133.67,
      "datetime": "2024-08-13 08:00"
    },
    {
      "timestamp": 1723528800,
      "price": 117.89,
      "datetime": "2024-08-13 09:00"
    },
    {
      "timestamp": 1723532400,
      "price": 70.66,
      "datetime": "2024-08-13 10:00"
    },
    {
      "timestamp": 1723536000,
      "price": 34.79,
      "datetime": "2024-08-13 11:00"
    },
    {
      "timestamp": 1723539600,
      "price": 24.6,
      "datetime": "2024-08-13 12:00"
    },
    {
      "timestamp": 1723543200,
      "price": 25.43,
      "datetime": "2024-08-13 13:00"
    },
    {
      "timestamp": 1723546800,
      "price": 27.64,
      "datetime": "2024-08-13 14:00"
    },
    {
      "timestamp": 1723550400,
      "price": 49.18,
      "datetime": "2024-08-13 15:00"
    },
    {
      "timestamp": 1723554000,
      "price": 21.19,
      "datetime": "2024-08-13 16:00"
    },
    {
      "timestamp": 1723557600,
      "price": 33.4,
      "datetime": "2024-08-13 17:00"
    },
    {
      "timestamp": 1723561200,
      "price": 160.0,
      "datetime": "2024-08-13 18:00"
    },
    {
      "timestamp": 1723564800,
      "price": 160.09,
      "datetime": "2024-08-13 19:00"
    },
    {
      "timestamp": 1723568400,
      "price": 300.01,
      "datetime": "2024-08-13 20:00"
    },
    {
      "timestamp": 1723572000,
      "price": 300.02,
      "datetime": "2024-08-13 21:00"
    },
    {
      "timestamp": 1723575600,
      "price": 160.09,
      "datetime": "2024-08-13 22:00"
    },
    {
      "timestamp": 1723579200,
      "price": 120.04,
      "datetime": "2024-08-13 23:00"
    },
    {
      "timestamp": 1723582800,
      "price": 97.5,
      "datetime": "2024-08-14 00:00"
    },
    {
      "timestamp": 1723586400,
      "price": 161.36,
      "datetime": "2024-08-14 01:00"
    },
    {
      "timestamp": 1723590000,
      "price": 160.77,
      "datetime": "2024-08-14 02:00"
    },
    {
      "timestamp": 1723593600,
      "price": 83.03,
      "datetime": "2024-08-14 03:00"
    },
    {
      "timestamp": 1723597200,
      "price": 89.51,
      "datetime": "2024-08-14 04:00"
    },
    {
      "timestamp": 1723600800,
      "price": 185.07,
      "datetime": "2024-08-14 05:00"
    },
    {
      "timestamp": 1723604400,
      "price": 140.06,
      "datetime": "2024-08-14 06:00"
    },
    {
      "timestamp": 1723608000,
      "price": 250.08,
      "datetime": "2024-08-14 07:00"
    },
    {
      "timestamp": 1723611600,
      "price": 250.05,
      "datetime": "2024-08-14 08:00"
    },
    {
      "timestamp": 1723615200,
      "price": 140.09,
      "datetime": "2024-08-14 09:00"
    },
    {
      "timestamp": 1723618800,
      "price": 115.97,
      "datetime": "2024-08-14 10:00"
    },
    {
      "timestamp": 1723622400,
      "price": 82.73,
      "datetime": "2024-08-14 11:00"
    },
    {
      "timestamp": 1723626000,
      "price": 77.15,
      "datetime": "2024-08-14 12:00"
    },
    {
      "timestamp": 1723629600,
      "price": 68.85,
      "datetime": "2024-08-14 13:00"
    },
    {
      "timestamp": 1723633200,
      "price": 75.56,
      "datetime": "2024-08-14 14:00"
    },
    {
      "timestamp": 1723636800,
      "price": 86.38,
      "datetime": "2024-08-14 15:00"
    },
    {
      "timestamp": 1723640400,
      "price": 76.7,
      "datetime": "2024-08-14 16:00"
    },
    {
      "timestamp": 1723644000,
      "price": 193.75,
      "datetime": "2024-08-14 17:00"
    },
    {
      "timestamp": 1723647600,
      "price": 115.13,
      "datetime": "2024-08-14 18:00"
    },
    {
      "timestamp": 1723651200,
      "price": 146.82,
      "datetime": "2024-08-14 19:00"
    },
    {
      "timestamp": 1723654800,
      "price": 212.28,
      "datetime": "2024-08-14 20:00"
    },
    {
      "timestamp": 1723658400,
      "price": 230.38,
      "datetime": "2024-08-14 21:00"
    },
    {
      "timestamp": 1723662000,
      "price": 141.93,
      "datetime": "2024-08-14 22:00"
    },
    {
      "timestamp": 1723665600,
      "price": 117.68,
      "datetime": "2024-08-14 23:00"
    },
    {
      "timestamp": 1723669200,
      "price": 108.38,
      "datetime": "2024-08-15 00:00"
    },
    {
      "timestamp": 1723672800,
      "price": 230.97,
      "datetime": "2024-08-15 01:00"
    },
    {
      "timestamp": 1723676400,
      "price": 104.13,
      "datetime": "2024-08-15 02:00"
    },
    {
      "timestamp": 1723680000,
      "price": 95.05,
      "datetime": "2024-08-15 03:00"
    },
    {
      "timestamp": 1723683600,
      "price": 92.89,
      "datetime": "2024-08-15 04:00"
    },
    {
      "timestamp": 1723687200,
      "price": 94.2,
      "datetime": "2024-08-15 05:00"
    },
    {
      "timestamp": 1723690800,
      "price": 104.78,
      "datetime": "2024-08-15 06:00"
    },
    {
      "timestamp": 1723694400,
      "price": 108.32,
      "datetime": "2024-08-15 07:00"
    },
    {
      "timestamp": 1723698000,
      "price": 116.05,
      "datetime": "2024-08-15 08:00"
    },
    {
      "timestamp": 1723701600,
      "price": 112.21,
      "datetime": "2024-08-15 09:00"
    },
    {
      "timestamp": 1723705200,
      "price": 91.04,
      "datetime": "2024-08-15 10:00"
    },
    {
      "timestamp": 1723708800,
      "price": 33.12,
      "datetime": "2024-08-15 11:00"
    },
    {
      "timestamp": 1723712400,
      "price": 15.18,
      "datetime": "2024-08-15 12:00"
    },
    {
      "timestamp": 1723716000,
      "price": 9.86,
      "datetime": "2024-08-15 13:00"
    },
    {
      "timestamp": 1723719600,
      "price": 4.99,
      "datetime": "2024-08-15 14:00"
    },
    {
      "timestamp": 1723723200,
      "price": 35.93,
      "datetime": "2024-08-15 15:00"
    },
    {
      "timestamp": 1723726800,
      "price": 4.36,
      "datetime": "2024-08-15 16:00"
    },
    {
      "timestamp": 1723730400,
      "price": 60.84,
      "datetime": "2024-08-15 17:00"
    },
    {
      "timestamp": 1723734000,
      "price": 12.14,
      "datetime": "2024-08-15 18:00"
    },
    {
      "timestamp": 1723737600,
      "price": 140.06,
      "datetime": "2024-08-15 19:00"
    },
    {
      "timestamp": 1723741200,
      "price": 165.04,
      "datetime": "2024-08-15 20:00"
    },
    {
      "timestamp": 1723744800,
      "price": 206.09,
      "datetime": "2024-08-15 21:00"
    },
    {
      "timestamp": 1723748400,
      "price": 159.02,
      "datetime": "2024-08-15 22:00"
    },
    {
      "timestamp": 1723752000,
      "price": 138.58,
      "datetime": "2024-08-15 23:00"
    },
    {
      "timestamp": 1723755600,
      "price": 105.33,
      "datetime": "2024-08-16 00:00"
    },
    {
      "timestamp": 1723759200,
      "price": 112.35,
      "datetime": "2024-08-16 01:00"
    },
    {
      "timestamp": 1723762800,
      "price": 93.75,
      "datetime": "2024-08-16 02:00"
    },
    {
      "timestamp": 1723766400,
      "price": 92.22,
      "datetime": "2024-08-16 03:00"
    },
    {
      "timestamp": 1723770000,
      "price": 92.47,
      "datetime": "2024-08-16 04:00"
    },
    {
      "timestamp": 1723773600,
      "price": 93.2,
      "datetime": "2024-08-16 05:00"
    },
    {
      "timestamp": 1723777200,
      "price": 100.26,
      "datetime": "2024-08-16 06:00"
    },
    {
      "timestamp": 1723780800,
      "price": 127.33,
      "datetime": "2024-08-16 07:00"
    },
    {
      "timestamp": 1723784400,
      "price": 133.85,
      "datetime": "2024-08-16 08:00"
    },
    {
      "timestamp": 1723788000,
      "price": 124.2,
      "datetime": "2024-08-16 09:00"
    },
    {
      "timestamp": 1723791600,
      "price": 100.01,
      "datetime": "2024-08-16 10:00"
    },
    {
      "timestamp": 1723795200,
      "price": 75.05,
      "datetime": "2024-08-16 11:00"
    },
    {
      "timestamp": 1723798800,
      "price": 56.32,
      "datetime": "2024-08-16 12:00"
    },
    {
      "timestamp": 1723802400,
      "price": 25.14,
      "datetime": "2024-08-16 13:00"
    },
    {
      "timestamp": 1723806000,
      "price": 53.81,
      "datetime": "2024-08-16 14:00"
    },
    {
      "timestamp": 1723809600,
      "price": 43.02,
      "datetime": "2024-08-16 15:00"
    },
    {
      "timestamp": 1723813200,
      "price": 53.84,
      "datetime": "2024-08-16 16:00"
    },
    {
      "timestamp": 1723816800,
      "price": 77.11,
      "datetime": "2024-08-16 17:00"
    },
    {
      "timestamp": 1723820400,
      "price": 114.66,
      "datetime": "2024-08-16 18:00"
    },
    {
      "timestamp": 1723824000,
      "price": 186.48,
      "datetime": "2024-08-16 19:00"
    },
    {
      "timestamp": 1723827600,
      "price": 258.39,
      "datetime": "2024-08-16 20:00"
    },
    {
      "timestamp": 1723831200,
      "price": 237.29,
      "datetime": "2024-08-16 21:00"
    },
    {
      "timestamp": 1723834800,
      "price": 167.71,
      "datetime": "2024-08-16 22:00"
    },
    {
      "timestamp": 1723838400,
      "price": 151.61,
      "datetime": "2024-08-16 23:00"
    },
    {
      "timestamp": 1723842000,
      "price": 119.46,
      "datetime": "2024-08-17 00:00"
    },
    {
      "timestamp": 1723845600,
      "price": 115.29,
      "datetime": "2024-08-17 01:00"
    },
    {
      "timestamp": 1723849200,
      "price": 110.14,
      "datetime": "2024-08-17 02:00"
    },
    {
      "timestamp": 1723852800,
      "price": 103.0,
      "datetime": "2024-08-17 03:00"
    },
    {
      "timestamp": 1723856400,
      "price": 105.44,
      "datetime": "2024-08-17 04:00"
    },
    {
      "timestamp": 1723860000,
      "price": 112.1,
      "datetime": "2024-08-17 05:00"
    },
    {
      "timestamp": 1723863600,
      "price": 110.65,
      "datetime": "2024-08-17 06:00"
    },
    {
      "timestamp": 1723867200,
      "price": 106.18,
      "datetime": "2024-08-17 07:00"
    },
    {
      "timestamp": 1723870800,
      "price": 103.43,
      "datetime": "2024-08-17 08:00"
    },
    {
      "timestamp": 1723874400,
      "price": 103.06,
      "datetime": "2024-08-17 09:00"
    },
    {
      "timestamp": 1723878000,
      "price": 83.8,
      "datetime": "2024-08-17 10:00"
    },
    {
      "timestamp": 1723881600,
      "price": 69.49,
      "datetime": "2024-08-17 11:00"
    },
    {
      "timestamp": 1723885200,
      "price": 56.81,
      "datetime": "2024-08-17 12:00"
    },
    {
      "timestamp": 1723888800,
      "price": 47.92,
      "datetime": "2024-08-17 13:00"
    },
    {
      "timestamp": 1723892400,
      "price": 44.12,
      "datetime": "2024-08-17 14:00"
    },
    {
      "timestamp": 1723896000,
      "price": 53.36,
      "datetime": "2024-08-17 15:00"
    },
    {
      "timestamp": 1723899600,
      "price": 59.24,
      "datetime": "2024-08-17 16:00"
    },
    {
      "timestamp": 1723903200,
      "price": 73.08,
      "datetime": "2024-08-17 17:00"
    },
    {
      "timestamp": 1723906800,
      "price": 117.72,
      "datetime": "2024-08-17 18:00"
    },
    {
      "timestamp": 1723910400,
      "price": 141.08,
      "datetime": "2024-08-17 19:00"
    },
    {
      "timestamp": 1723914000,
      "price": 154.96,
      "datetime": "2024-08-17 20:00"
    },
    {
      "timestamp": 1723917600,
      "price": 178.5,
      "datetime": "2024-08-17 21:00"
    },
    {
      "timestamp": 1723921200,
      "price": 140.5,
      "datetime": "2024-08-17 22:00"
    },
    {
      "timestamp": 1723924800,
      "price": 119.82,
      "datetime": "2024-08-17 23:00"
    },
    {
      "timestamp": 1723928400,
      "price": 108.61,
      "datetime": "2024-08-18 00:00"
    },
    {
      "timestamp": 1723932000,
      "price": 114.69,
      "datetime": "2024-08-18 01:00"
    },
    {
      "timestamp": 1723935600,
      "price": 112.41,
      "datetime": "2024-08-18 02:00"
    },
    {
      "timestamp": 1723939200,
      "price": 105.78,
      "datetime": "2024-08-18 03:00"
    },
    {
      "timestamp": 1723942800,
      "price": 105.76,
      "datetime": "2024-08-18 04:00"
    },
    {
      "timestamp": 1723946400,
      "price": 104.28,
      "datetime": "2024-08-18 05:00"
    },
    {
      "timestamp": 1723950000,
      "price": 104.42,
      "datetime": "2024-08-18 06:00"
    },
    {
      "timestamp": 1723953600,
      "price": 98.81,
      "datetime": "2024-08-18 07:00"
    },
    {
      "timestamp": 1723957200,
      "price": 94.4,
      "datetime": "2024-08-18 08:00"
    },
    {
      "timestamp": 1723960800,
      "price": 87.65,
      "datetime": "2024-08-18 09:00"
    },
    {
      "timestamp": 1723964400,
      "price": 81.52,
      "datetime": "2024-08-18 10:00"
    },
    {
      "timestamp": 1723968000,
      "price": 69.71,
      "datetime": "2024-08-18 11:00"
    },
    {
      "timestamp": 1723971600,
      "price": 69.04,
      "datetime": "2024-08-18 12:00"
    },
    {
      "timestamp": 1723975200,
      "price": 64.01,
      "datetime": "2024-08-18 13:00"
    },
    {
      "timestamp": 1723978800,
      "price": 32.6,
      "datetime": "2024-08-18 14:00"
    },
    {
      "timestamp": 1723982400,
      "price": 16.86,
      "datetime": "2024-08-18 15:00"
    },
    {
      "timestamp": 1723986000,
      "price": 50.05,
      "datetime": "2024-08-18 16:00"
    },
    {
      "timestamp": 1723989600,
      "price": 94.0,
      "datetime": "2024-08-18 17:00"
    },
    {
      "timestamp": 1723993200,
      "price": 102.54,
      "datetime": "2024-08-18 18:00"
    },
    {
      "timestamp": 1723996800,
      "price": 113.93,
      "datetime": "2024-08-18 19:00"
    },
    {
      "timestamp": 1724000400,
      "price": 162.36,
      "datetime": "2024-08-18 20:00"
    },
    {
      "timestamp": 1724004000,
      "price": 146.54,
      "datetime": "2024-08-18 21:00"
    },
    {
      "timestamp": 1724007600,
      "price": 122.88,
      "datetime": "2024-08-18 22:00"
    },
    {
      "timestamp": 1724011200,
      "price": 121.36,
      "datetime": "2024-08-18 23:00"
    },
    {
      "timestamp": 1724014800,
      "price": 109.04,
      "datetime": "2024-08-19 00:00"
    },
    {
      "timestamp": 1724018400,
      "price": 106.69,
      "datetime": "2024-08-19 01:00"
    },
    {
      "timestamp": 1724022000,
      "price": 96.93,
      "datetime": "2024-08-19 02:00"
    },
    {
      "timestamp": 1724025600,
      "price": 90.89,
      "datetime": "2024-08-19 03:00"
    },
    {
      "timestamp": 1724029200,
      "price": 85.05,
      "datetime": "2024-08-19 04:00"
    },
    {
      "timestamp": 1724032800,
      "price": 86.03,
      "datetime": "2024-08-19 05:00"
    },
    {
      "timestamp": 1724036400,
      "price": 92.48,
      "datetime": "2024-08-19 06:00"
    },
    {
      "timestamp": 1724040000,
      "price": 131.27,
      "datetime": "2024-08-19 07:00"
    },
    {
      "timestamp": 1724043600,
      "price": 154.13,
      "datetime": "2024-08-19 08:00"
    },
    {
      "timestamp": 1724047200,
      "price": 155.71,
      "datetime": "2024-08-19 09:00"
    },
    {
      "timestamp": 1724050800,
      "price": 172.99,
      "datetime": "2024-08-19 10:00"
    },
    {
      "timestamp": 1724054400,
      "price": 169.79,
      "datetime": "2024-08-19 11:00"
    },
    {
      "timestamp": 1724058000,
      "price": 115.91,
      "datetime": "2024-08-19 12:00"
    },
    {
      "timestamp": 1724061600,
      "price": 88.9,
      "datetime": "2024-08-19 13:00"
    },
    {
      "timestamp": 1724065200,
      "price": 80.65,
      "datetime": "2024-08-19 14:00"
    },
    {
      "timestamp": 1724068800,
      "price": 81.8,
      "datetime": "2024-08-19 15:00"
    },
    {
      "timestamp": 1724072400,
      "price": 93.64,
      "datetime": "2024-08-19 16:00"
    },
    {
      "timestamp": 1724076000,
      "price": 122.9,
      "datetime": "2024-08-19 17:00"
    },
    {
      "timestamp": 1724079600,
      "price": 139.82,
      "datetime": "2024-08-19 18:00"
    },
    {
      "timestamp": 1724083200,
      "price": 215.3,
      "datetime": "2024-08-19 19:00"
    },
    {
      "timestamp": 1724086800,
      "price": 250.1,
      "datetime": "2024-08-19 20:00"
    },
    {
      "timestamp": 1724090400,
      "price": 240.09,
      "datetime": "2024-08-19 21:00"
    },
    {
      "timestamp": 1724094000,
      "price": 190.67,
      "datetime": "2024-08-19 22:00"
    },
    {
      "timestamp": 1724097600,
      "price": 126.16,
      "datetime": "2024-08-19 23:00"
    },
    {
      "timestamp": 1724101200,
      "price": 100.44,
      "datetime": "2024-08-20 00:00"
    },
    {
      "timestamp": 1724104800,
      "price": 106.75,
      "datetime": "2024-08-20 01:00"
    },
    {
      "timestamp": 1724108400,
      "price": 95.89,
      "datetime": "2024-08-20 02:00"
    },
    {
      "timestamp": 1724112000,
      "price": 93.76,
      "datetime": "2024-08-20 03:00"
    },
    {
      "timestamp": 1724115600,
      "price": 94.59,
      "datetime": "2024-08-20 04:00"
    },
    {
      "timestamp": 1724119200,
      "price": 97.81,
      "datetime": "2024-08-20 05:00"
    },
    {
      "timestamp": 1724122800,
      "price": 114.99,
      "datetime": "2024-08-20 06:00"
    },
    {
      "timestamp": 1724126400,
      "price": 141.78,
      "datetime": "2024-08-20 07:00"
    },
    {
      "timestamp": 1724130000,
      "price": 139.02,
      "datetime": "2024-08-20 08:00"
    },
    {
      "timestamp": 1724133600,
      "price": 122.66,
      "datetime": "2024-08-20 09:00"
    },
    {
      "timestamp": 1724137200,
      "price": 102.6,
      "datetime": "2024-08-20 10:00"
    },
    {
      "timestamp": 1724140800,
      "price": 83.89,
      "datetime": "2024-08-20 11:00"
    },
    {
      "timestamp": 1724144400,
      "price": 65.76,
      "datetime": "2024-08-20 12:00"
    },
    {
      "timestamp": 1724148000,
      "price": 54.71,
      "datetime": "2024-08-20 13:00"
    },
    {
      "timestamp": 1724151600,
      "price": 71.03,
      "datetime": "2024-08-20 14:00"
    },
    {
      "timestamp": 1724155200,
      "price": 62.78,
      "datetime": "2024-08-20 15:00"
    },
    {
      "timestamp": 1724158800,
      "price": 88.68,
      "datetime": "2024-08-20 16:00"
    },
    {
      "timestamp": 1724162400,
      "price": 114.65,
      "datetime": "2024-08-20 17:00"
    },
    {
      "timestamp": 1724166000,
      "price": 138.34,
      "datetime": "2024-08-20 18:00"
    },
    {
      "timestamp": 1724169600,
      "price": 192.51,
      "datetime": "2024-08-20 19:00"
    },
    {
      "timestamp": 1724173200,
      "price": 287.45,
      "datetime": "2024-08-20 20:00"
    },
    {
      "timestamp": 1724176800,
      "price": 321.28,
      "datetime": "2024-08-20 21:00"
    },
    {
      "timestamp": 1724180400,
      "price": 174.1,
      "datetime": "2024-08-20 22:00"
    },
    {
      "timestamp": 1724184000,
      "price": 139.02,
      "datetime": "2024-08-20 23:00"
    },
    {
      "timestamp": 1724187600,
      "price": 109.21,
      "datetime": "2024-08-21 00:00"
    },
    {
      "timestamp": 1724191200,
      "price": 118.26,
      "datetime": "2024-08-21 01:00"
    },
    {
      "timestamp": 1724194800,
      "price": 99.46,
      "datetime": "2024-08-21 02:00"
    },
    {
      "timestamp": 1724198400,
      "price": 96.52,
      "datetime": "2024-08-21 03:00"
    },
    {
      "timestamp": 1724202000,
      "price": 98.25,
      "datetime": "2024-08-21 04:00"
    },
    {
      "timestamp": 1724205600,
      "price": 98.06,
      "datetime": "2024-08-21 05:00"
    },
    {
      "timestamp": 1724209200,
      "price": 106.25,
      "datetime": "2024-08-21 06:00"
    },
    {
      "timestamp": 1724212800,
      "price": 141.03,
      "datetime": "2024-08-21 07:00"
    },
    {
      "timestamp": 1724216400,
      "price": 152.27,
      "datetime": "2024-08-21 08:00"
    },
    {
      "timestamp": 1724220000,
      "price": 174.3,
      "datetime": "2024-08-21 09:00"
    },
    {
      "timestamp": 1724223600,
      "price": 156.02,
      "datetime": "2024-08-21 10:00"
    },
    {
      "timestamp": 1724227200,
      "price": 133.3,
      "datetime": "2024-08-21 11:00"
    },
    {
      "timestamp": 1724230800,
      "price": 117.5,
      "datetime": "2024-08-21 12:00"
    },
    {
      "timestamp": 1724234400,
      "price": 103.07,
      "datetime": "2024-08-21 13:00"
    },
    {
      "timestamp": 1724238000,
      "price": 104.72,
      "datetime": "2024-08-21 14:00"
    },
    {
      "timestamp": 1724241600,
      "price": 97.26,
      "datetime": "2024-08-21 15:00"
    },
    {
      "timestamp": 1724245200,
      "price": 140.39,
      "datetime": "2024-08-21 16:00"
    },
    {
      "timestamp": 1724248800,
      "price": 189.99,
      "datetime": "2024-08-21 17:00"
    },
    {
      "timestamp": 1724252400,
      "price": 141.03,
      "datetime": "2024-08-21 18:00"
    },
    {
      "timestamp": 1724256000,
      "price": 150.84,
      "datetime": "2024-08-21 19:00"
    },
    {
      "timestamp": 1724259600,
      "price": 156.06,
      "datetime": "2024-08-21 20:00"
    },
    {
      "timestamp": 1724263200,
      "price": 163.57,
      "datetime": "2024-08-21 21:00"
    },
    {
      "timestamp": 1724266800,
      "price": 138.67,
      "datetime": "2024-08-21 22:00"
    },
    {
      "timestamp": 1724270400,
      "price": 107.84,
      "datetime": "2024-08-21 23:00"
    },
    {
      "timestamp": 1724274000,
      "price": 91.7,
      "datetime": "2024-08-22 00:00"
    },
    {
      "timestamp": 1724277600,
      "price": 73.04,
      "datetime": "2024-08-22 01:00"
    },
    {
      "timestamp": 1724281200,
      "price": 66.58,
      "datetime": "2024-08-22 02:00"
    },
    {
      "timestamp": 1724284800,
      "price": 79.73,
      "datetime": "2024-08-22 03:00"
    },
    {
      "timestamp": 1724288400,
      "price": 80.02,
      "datetime": "2024-08-22 04:00"
    },
    {
      "timestamp": 1724292000,
      "price": 69.11,
      "datetime": "2024-08-22 05:00"
    },
    {
      "timestamp": 1724295600,
      "price": 81.45,
      "datetime": "2024-08-22 06:00"
    },
    {
      "timestamp": 1724299200,
      "price": 112.75,
      "datetime": "2024-08-22 07:00"
    },
    {
      "timestamp": 1724302800,
      "price": 135.01,
      "datetime": "2024-08-22 08:00"
    },
    {
      "timestamp": 1724306400,
      "price": 135.09,
      "datetime": "2024-08-22 09:00"
    },
    {
      "timestamp": 1724310000,
      "price": 158.03,
      "datetime": "2024-08-22 10:00"
    },
    {
      "timestamp": 1724313600,
      "price": 65.05,
      "datetime": "2024-08-22 11:00"
    },
    {
      "timestamp": 1724317200,
      "price": 65.06,
      "datetime": "2024-08-22 12:00"
    },
    {
      "timestamp": 1724320800,
      "price": 65.09,
      "datetime": "2024-08-22 13:00"
    },
    {
      "timestamp": 1724324400,
      "price": 87.27,
      "datetime": "2024-08-22 14:00"
    },
    {
      "timestamp": 1724328000,
      "price": 71.58,
      "datetime": "2024-08-22 15:00"
    },
    {
      "timestamp": 1724331600,
      "price": 81.68,
      "datetime": "2024-08-22 16:00"
    },
    {
      "timestamp": 1724335200,
      "price": 86.36,
      "datetime": "2024-08-22 17:00"
    },
    {
      "timestamp": 1724338800,
      "price": 106.9,
      "datetime": "2024-08-22 18:00"
    },
    {
      "timestamp": 1724342400,
      "price": 177.06,
      "datetime": "2024-08-22 19:00"
    },
    {
      "timestamp": 1724346000,
      "price": 228.53,
      "datetime": "2024-08-22 20:00"
    },
    {
      "timestamp": 1724349600,
      "price": 271.58,
      "datetime": "2024-08-22 21:00"
    },
    {
      "timestamp": 1724353200,
      "price": 176.05,
      "datetime": "2024-08-22 22:00"
    },
    {
      "timestamp": 1724356800,
      "price": 118.81,
      "datetime": "2024-08-22 23:00"
    },
    {
      "timestamp": 1724360400,
      "price": 90.95,
      "datetime": "2024-08-23 00:00"
    },
    {
      "timestamp": 1724364000,
      "price": 109.3,
      "datetime": "2024-08-23 01:00"
    },
    {
      "timestamp": 1724367600,
      "price": 51.65,
      "datetime": "2024-08-23 02:00"
    },
    {
      "timestamp": 1724371200,
      "price": 93.58,
      "datetime": "2024-08-23 03:00"
    },
    {
      "timestamp": 1724374800,
      "price": 93.84,
      "datetime": "2024-08-23 04:00"
    },
    {
      "timestamp": 1724378400,
      "price": 43.09,
      "datetime": "2024-08-23 05:00"
    },
    {
      "timestamp": 1724382000,
      "price": 98.88,
      "datetime": "2024-08-23 06:00"
    },
    {
      "timestamp": 1724385600,
      "price": 137.88,
      "datetime": "2024-08-23 07:00"
    },
    {
      "timestamp": 1724389200,
      "price": 123.43,
      "datetime": "2024-08-23 08:00"
    },
    {
      "timestamp": 1724392800,
      "price": 160.09,
      "datetime": "2024-08-23 09:00"
    },
    {
      "timestamp": 1724396400,
      "price": 160.01,
      "datetime": "2024-08-23 10:00"
    },
    {
      "timestamp": 1724400000,
      "price": 141.44,
      "datetime": "2024-08-23 11:00"
    },
    {
      "timestamp": 1724403600,
      "price": 49.99,
      "datetime": "2024-08-23 12:00"
    },
    {
      "timestamp": 1724407200,
      "price": 60.75,
      "datetime": "2024-08-23 13:00"
    },
    {
      "timestamp": 1724410800,
      "price": 43.92,
      "datetime": "2024-08-23 14:00"
    },
    {
      "timestamp": 1724414400,
      "price": 40.05,
      "datetime": "2024-08-23 15:00"
    },
    {
      "timestamp": 1724418000,
      "price": 55.6,
      "datetime": "2024-08-23 16:00"
    },
    {
      "timestamp": 1724421600,
      "price": 118.8,
      "datetime": "2024-08-23 17:00"
    },
    {
      "timestamp": 1724425200,
      "price": 118.79,
      "datetime": "2024-08-23 18:00"
    },
    {
      "timestamp": 1724428800,
      "price": 123.05,
      "datetime": "2024-08-23 19:00"
    },
    {
      "timestamp": 1724432400,
      "price": 160.05,
      "datetime": "2024-08-23 20:00"
    },
    {
      "timestamp": 1724436000,
      "price": 163.63,
      "datetime": "2024-08-23 21:00"
    },
    {
      "timestamp": 1724439600,
      "price": 132.56,
      "datetime": "2024-08-23 22:00"
    },
    {
      "timestamp": 1724443200,
      "price": 122.79,
      "datetime": "2024-08-23 23:00"
    },
    {
      "timestamp": 1724446800,
      "price": 94.76,
      "datetime": "2024-08-24 00:00"
    },
    {
      "timestamp": 1724450400,
      "price": 25.1,
      "datetime": "2024-08-24 01:00"
    },
    {
      "timestamp": 1724454000,
      "price": 46.93,
      "datetime": "2024-08-24 02:00"
    },
    {
      "timestamp": 1724457600,
      "price": 4.1,
      "datetime": "2024-08-24 03:00"
    },
    {
      "timestamp": 1724461200,
      "price": 70.03,
      "datetime": "2024-08-24 04:00"
    },
    {
      "timestamp": 1724464800,
      "price": 111.29,
      "datetime": "2024-08-24 05:00"
    },
    {
      "timestamp": 1724468400,
      "price": 114.61,
      "datetime": "2024-08-24 06:00"
    },
    {
      "timestamp": 1724472000,
      "price": 117.16,
      "datetime": "2024-08-24 07:00"
    },
    {
      "timestamp": 1724475600,
      "price": 104.0,
      "datetime": "2024-08-24 08:00"
    },
    {
      "timestamp": 1724479200,
      "price": 77.4,
      "datetime": "2024-08-24 09:00"
    },
    {
      "timestamp": 1724482800,
      "price": 15.0,
      "datetime": "2024-08-24 10:00"
    },
    {
      "timestamp": 1724486400,
      "price": -0.01,
      "datetime": "2024-08-24 11:00"
    },
    {
      "timestamp": 1724490000,
      "price": 5.0,
      "datetime": "2024-08-24 12:00"
    },
    {
      "timestamp": 1724493600,
      "price": 7.49,
      "datetime": "2024-08-24 13:00"
    },
    {
      "timestamp": 1724497200,
      "price": 27.8,
      "datetime": "2024-08-24 14:00"
    },
    {
      "timestamp": 1724500800,
      "price": 4.55,
      "datetime": "2024-08-24 15:00"
    },
    {
      "timestamp": 1724504400,
      "price": 30.01,
      "datetime": "2024-08-24 16:00"
    },
    {
      "timestamp": 1724508000,
      "price": 83.3,
      "datetime": "2024-08-24 17:00"
    },
    {
      "timestamp": 1724511600,
      "price": 144.41,
      "datetime": "2024-08-24 18:00"
    },
    {
      "timestamp": 1724515200,
      "price": 206.03,
      "datetime": "2024-08-24 19:00"
    },
    {
      "timestamp": 1724518800,
      "price": 217.32,
      "datetime": "2024-08-24 20:00"
    },
    {
      "timestamp": 1724522400,
      "price": 202.33,
      "datetime": "2024-08-24 21:00"
    },
    {
      "timestamp": 1724526000,
      "price": 140.44,
      "datetime": "2024-08-24 22:00"
    },
    {
      "timestamp": 1724529600,
      "price": 114.86,
      "datetime": "2024-08-24 23:00"
    },
    {
      "timestamp": 1724533200,
      "price": 85.04,
      "datetime": "2024-08-25 00:00"
    },
    {
      "timestamp": 1724536800,
      "price": 51.18,
      "datetime": "2024-08-25 01:00"
    },
    {
      "timestamp": 1724540400,
      "price": -0.01,
      "datetime": "2024-08-25 02:00"
    },
    {
      "timestamp": 1724544000,
      "price": 0.42,
      "datetime": "2024-08-25 03:00"
    },
    {
      "timestamp": 1724547600,
      "price": 0.01,
      "datetime": "2024-08-25 04:00"
    },
    {
      "timestamp": 1724551200,
      "price": -1.75,
      "datetime": "2024-08-25 05:00"
    },
    {
      "timestamp": 1724554800,
      "price": -1.75,
      "datetime": "2024-08-25 06:00"
    },
    {
      "timestamp": 1724558400,
      "price": 2.99,
      "datetime": "2024-08-25 07:00"
    },
    {
      "timestamp": 1724562000,
      "price": -0.15,
      "datetime": "2024-08-25 08:00"
    },
    {
      "timestamp": 1724565600,
      "price": -0.9,
      "datetime": "2024-08-25 09:00"
    },
    {
      "timestamp": 1724569200,
      "price": -1.54,
      "datetime": "2024-08-25 10:00"
    },
    {
      "timestamp": 1724572800,
      "price": -6.07,
      "datetime": "2024-08-25 11:00"
    },
    {
      "timestamp": 1724576400,
      "price": -10.1,
      "datetime": "2024-08-25 12:00"
    },
    {
      "timestamp": 1724580000,
      "price": -15.5,
      "datetime": "2024-08-25 13:00"
    },
    {
      "timestamp": 1724583600,
      "price": -19.96,
      "datetime": "2024-08-25 14:00"
    },
    {
      "timestamp": 1724587200,
      "price": -10.01,
      "datetime": "2024-08-25 15:00"
    },
    {
      "timestamp": 1724590800,
      "price": -9.95,
      "datetime": "2024-08-25 16:00"
    },
    {
      "timestamp": 1724594400,
      "price": 0.02,
      "datetime": "2024-08-25 17:00"
    },
    {
      "timestamp": 1724598000,
      "price": 4.07,
      "datetime": "2024-08-25 18:00"
    },
    {
      "timestamp": 1724601600,
      "price": 95.6,
      "datetime": "2024-08-25 19:00"
    },
    {
      "timestamp": 1724605200,
      "price": 172.99,
      "datetime": "2024-08-25 20:00"
    },
    {
      "timestamp": 1724608800,
      "price": 233.62,
      "datetime": "2024-08-25 21:00"
    },
    {
      "timestamp": 1724612400,
      "price": 198.26,
      "datetime": "2024-08-25 22:00"
    },
    {
      "timestamp": 1724616000,
      "price": 157.69,
      "datetime": "2024-08-25 23:00"
    },
    {
      "timestamp": 1724619600,
      "price": 110.79,
      "datetime": "2024-08-26 00:00"
    },
    {
      "timestamp": 1724623200,
      "price": 105.46,
      "datetime": "2024-08-26 01:00"
    },
    {
      "timestamp": 1724626800,
      "price": 93.44,
      "datetime": "2024-08-26 02:00"
    },
    {
      "timestamp": 1724630400,
      "price": 89.48,
      "datetime": "2024-08-26 03:00"
    },
    {
      "timestamp": 1724634000,
      "price": 87.2,
      "datetime": "2024-08-26 04:00"
    },
    {
      "timestamp": 1724637600,
      "price": 91.2,
      "datetime": "2024-08-26 05:00"
    },
    {
      "timestamp": 1724641200,
      "price": 124.08,
      "datetime": "2024-08-26 06:00"
    },
    {
      "timestamp": 1724644800,
      "price": 165.01,
      "datetime": "2024-08-26 07:00"
    },
    {
      "timestamp": 1724648400,
      "price": 165.02,
      "datetime": "2024-08-26 08:00"
    },
    {
      "timestamp": 1724652000,
      "price": 128.96,
      "datetime": "2024-08-26 09:00"
    },
    {
      "timestamp": 1724655600,
      "price": 106.78,
      "datetime": "2024-08-26 10:00"
    },
    {
      "timestamp": 1724659200,
      "price": 87.19,
      "datetime": "2024-08-26 11:00"
    },
    {
      "timestamp": 1724662800,
      "price": 84.69,
      "datetime": "2024-08-26 12:00"
    },
    {
      "timestamp": 1724666400,
      "price": 91.59,
      "datetime": "2024-08-26 13:00"
    },
    {
      "timestamp": 1724670000,
      "price": 99.75,
      "datetime": "2024-08-26 14:00"
    },
    {
      "timestamp": 1724673600,
      "price": 93.22,
      "datetime": "2024-08-26 15:00"
    },
    {
      "timestamp": 1724677200,
      "price": 109.21,
      "datetime": "2024-08-26 16:00"
    },
    {
      "timestamp": 1724680800,
      "price": 124.48,
      "datetime": "2024-08-26 17:00"
    },
    {
      "timestamp": 1724684400,
      "price": 145.57,
      "datetime": "2024-08-26 18:00"
    },
    {
      "timestamp": 1724688000,
      "price": 183.39,
      "datetime": "2024-08-26 19:00"
    },
    {
      "timestamp": 1724691600,
      "price": 266.21,
      "datetime": "2024-08-26 20:00"
    },
    {
      "timestamp": 1724695200,
      "price": 304.99,
      "datetime": "2024-08-26 21:00"
    },
    {
      "timestamp": 1724698800,
      "price": 163.77,
      "datetime": "2024-08-26 22:00"
    },
    {
      "timestamp": 1724702400,
      "price": 118.71,
      "datetime": "2024-08-26 23:00"
    },
    {
      "timestamp": 1724706000,
      "price": 110.2,
      "datetime": "2024-08-27 00:00"
    },
    {
      "timestamp": 1724709600,
      "price": 105.78,
      "datetime": "2024-08-27 01:00"
    },
    {
      "timestamp": 1724713200,
      "price": 97.64,
      "datetime": "2024-08-27 02:00"
    },
    {
      "timestamp": 1724716800,
      "price": 95.44,
      "datetime": "2024-08-27 03:00"
    },
    {
      "timestamp": 1724720400,
      "price": 94.75,
      "datetime": "2024-08-27 04:00"
    },
    {
      "timestamp": 1724724000,
      "price": 96.44,
      "datetime": "2024-08-27 05:00"
    },
    {
      "timestamp": 1724727600,
      "price": 164.18,
      "datetime": "2024-08-27 06:00"
    },
    {
      "timestamp": 1724731200,
      "price": 148.25,
      "datetime": "2024-08-27 07:00"
    },
    {
      "timestamp": 1724734800,
      "price": 159.34,
      "datetime": "2024-08-27 08:00"
    },
    {
      "timestamp": 1724738400,
      "price": 116.42,
      "datetime": "2024-08-27 09:00"
    },
    {
      "timestamp": 1724742000,
      "price": 90.11,
      "datetime": "2024-08-27 10:00"
    },
    {
      "timestamp": 1724745600,
      "price": 74.45,
      "datetime": "2024-08-27 11:00"
    },
    {
      "timestamp": 1724749200,
      "price": 50.71,
      "datetime": "2024-08-27 12:00"
    },
    {
      "timestamp": 1724752800,
      "price": 36.72,
      "datetime": "2024-08-27 13:00"
    },
    {
      "timestamp": 1724756400,
      "price": 35.15,
      "datetime": "2024-08-27 14:00"
    },
    {
      "timestamp": 1724760000,
      "price": 49.07,
      "datetime": "2024-08-27 15:00"
    },
    {
      "timestamp": 1724763600,
      "price": 5.0,
      "datetime": "2024-08-27 16:00"
    },
    {
      "timestamp": 1724767200,
      "price": 89.67,
      "datetime": "2024-08-27 17:00"
    },
    {
      "timestamp": 1724770800,
      "price": 127.44,
      "datetime": "2024-08-27 18:00"
    },
    {
      "timestamp": 1724774400,
      "price": 168.82,
      "datetime": "2024-08-27 19:00"
    },
    {
      "timestamp": 1724778000,
      "price": 288.9,
      "datetime": "2024-08-27 20:00"
    },
    {
      "timestamp": 1724781600,
      "price": 277.19,
      "datetime": "2024-08-27 21:00"
    },
    {
      "timestamp": 1724785200,
      "price": 134.66,
      "datetime": "2024-08-27 22:00"
    },
    {
      "timestamp": 1724788800,
      "price": 100.91,
      "datetime": "2024-08-27 23:00"
    },
    {
      "timestamp": 1724792400,
      "price": 90.83,
      "datetime": "2024-08-28 00:00"
    },
    {
      "timestamp": 1724796000,
      "price": 84.45,
      "datetime": "2024-08-28 01:00"
    },
    {
      "timestamp": 1724799600,
      "price": 87.49,
      "datetime": "2024-08-28 02:00"
    },
    {
      "timestamp": 1724803200,
      "price": 85.14,
      "datetime": "2024-08-28 03:00"
    },
    {
      "timestamp": 1724806800,
      "price": 90.83,
      "datetime": "2024-08-28 04:00"
    },
    {
      "timestamp": 1724810400,
      "price": 92.65,
      "datetime": "2024-08-28 05:00"
    },
    {
      "timestamp": 1724814000,
      "price": 180.01,
      "datetime": "2024-08-28 06:00"
    },
    {
      "timestamp": 1724817600,
      "price": 122.14,
      "datetime": "2024-08-28 07:00"
    },
    {
      "timestamp": 1724821200,
      "price": 129.65,
      "datetime": "2024-08-28 08:00"
    },
    {
      "timestamp": 1724824800,
      "price": 123.77,
      "datetime": "2024-08-28 09:00"
    },
    {
      "timestamp": 1724828400,
      "price": 98.04,
      "datetime": "2024-08-28 10:00"
    },
    {
      "timestamp": 1724832000,
      "price": 51.61,
      "datetime": "2024-08-28 11:00"
    },
    {
      "timestamp": 1724835600,
      "price": 23.25,
      "datetime": "2024-08-28 12:00"
    },
    {
      "timestamp": 1724839200,
      "price": 63.53,
      "datetime": "2024-08-28 13:00"
    },
    {
      "timestamp": 1724842800,
      "price": 117.95,
      "datetime": "2024-08-28 14:00"
    },
    {
      "timestamp": 1724846400,
      "price": 5.04,
      "datetime": "2024-08-28 15:00"
    },
    {
      "timestamp": 1724850000,
      "price": 72.43,
      "datetime": "2024-08-28 16:00"
    },
    {
      "timestamp": 1724853600,
      "price": 43.79,
      "datetime": "2024-08-28 17:00"
    },
    {
      "timestamp": 1724857200,
      "price": 143.48,
      "datetime": "2024-08-28 18:00"
    },
    {
      "timestamp": 1724860800,
      "price": 231.15,
      "datetime": "2024-08-28 19:00"
    },
    {
      "timestamp": 1724864400,
      "price": 361.73,
      "datetime": "2024-08-28 20:00"
    },
    {
      "timestamp": 1724868000,
      "price": 250.08,
      "datetime": "2024-08-28 21:00"
    },
    {
      "timestamp": 1724871600,
      "price": 129.66,
      "datetime": "2024-08-28 22:00"
    },
    {
      "timestamp": 1724875200,
      "price": 103.91,
      "datetime": "2024-08-28 23:00"
    },
    {
      "timestamp": 1724878800,
      "price": 90.84,
      "datetime": "2024-08-29 00:00"
    },
    {
      "timestamp": 1724882400,
      "price": 91.89,
      "datetime": "2024-08-29 01:00"
    },
    {
      "timestamp": 1724886000,
      "price": 94.76,
      "datetime": "2024-08-29 02:00"
    },
    {
      "timestamp": 1724889600,
      "price": 88.71,
      "datetime": "2024-08-29 03:00"
    },
    {
      "timestamp": 1724893200,
      "price": 87.36,
      "datetime": "2024-08-29 04:00"
    },
    {
      "timestamp": 1724896800,
      "price": 87.46,
      "datetime": "2024-08-29 05:00"
    },
    {
      "timestamp": 1724900400,
      "price": 101.92,
      "datetime": "2024-08-29 06:00"
    },
    {
      "timestamp": 1724904000,
      "price": 127.47,
      "datetime": "2024-08-29 07:00"
    },
    {
      "timestamp": 1724907600,
      "price": 134.87,
      "datetime": "2024-08-29 08:00"
    },
    {
      "timestamp": 1724911200,
      "price": 126.24,
      "datetime": "2024-08-29 09:00"
    },
    {
      "timestamp": 1724914800,
      "price": 108.8,
      "datetime": "2024-08-29 10:00"
    },
    {
      "timestamp": 1724918400,
      "price": 90.8,
      "datetime": "2024-08-29 11:00"
    },
    {
      "timestamp": 1724922000,
      "price": 80.9,
      "datetime": "2024-08-29 12:00"
    },
    {
      "timestamp": 1724925600,
      "price": 51.06,
      "datetime": "2024-08-29 13:00"
    },
    {
      "timestamp": 1724929200,
      "price": 26.6,
      "datetime": "2024-08-29 14:00"
    },
    {
      "timestamp": 1724932800,
      "price": 36.57,
      "datetime": "2024-08-29 15:00"
    },
    {
      "timestamp": 1724936400,
      "price": 84.47,
      "datetime": "2024-08-29 16:00"
    },
    {
      "timestamp": 1724940000,
      "price": 109.37,
      "datetime": "2024-08-29 17:00"
    },
    {
      "timestamp": 1724943600,
      "price": 158.31,
      "datetime": "2024-08-29 18:00"
    },
    {
      "timestamp": 1724947200,
      "price": 303.65,
      "datetime": "2024-08-29 19:00"
    },
    {
      "timestamp": 1724950800,
      "price": 407.42,
      "datetime": "2024-08-29 20:00"
    },
    {
      "timestamp": 1724954400,
      "price": 289.99,
      "datetime": "2024-08-29 21:00"
    },
    {
      "timestamp": 1724958000,
      "price": 160.06,
      "datetime": "2024-08-29 22:00"
    },
    {
      "timestamp": 1724961600,
      "price": 120.05,
      "datetime": "2024-08-29 23:00"
    },
    {
      "timestamp": 1724965200,
      "price": 113.93,
      "datetime": "2024-08-30 00:00"
    },
    {
      "timestamp": 1724968800,
      "price": 110.2,
      "datetime": "2024-08-30 01:00"
    },
    {
      "timestamp": 1724972400,
      "price": 100.08,
      "datetime": "2024-08-30 02:00"
    },
    {
      "timestamp": 1724976000,
      "price": 94.87,
      "datetime": "2024-08-30 03:00"
    },
    {
      "timestamp": 1724979600,
      "price": 94.11,
      "datetime": "2024-08-30 04:00"
    },
    {
      "timestamp": 1724983200,
      "price": 98.45,
      "datetime": "2024-08-30 05:00"
    },
    {
      "timestamp": 1724986800,
      "price": 113.18,
      "datetime": "2024-08-30 06:00"
    },
    {
      "timestamp": 1724990400,
      "price": 149.43,
      "datetime": "2024-08-30 07:00"
    },
    {
      "timestamp": 1724994000,
      "price": 157.99,
      "datetime": "2024-08-30 08:00"
    },
    {
      "timestamp": 1724997600,
      "price": 134.21,
      "datetime": "2024-08-30 09:00"
    },
    {
      "timestamp": 1725001200,
      "price": 113.7,
      "datetime": "2024-08-30 10:00"
    },
    {
      "timestamp": 1725004800,
      "price": 96.47,
      "datetime": "2024-08-30 11:00"
    },
    {
      "timestamp": 1725008400,
      "price": 88.59,
      "datetime": "2024-08-30 12:00"
    },
    {
      "timestamp": 1725012000,
      "price": 77.25,
      "datetime": "2024-08-30 13:00"
    },
    {
      "timestamp": 1725015600,
      "price": 71.14,
      "datetime": "2024-08-30 14:00"
    },
    {
      "timestamp": 1725019200,
      "price": 86.9,
      "datetime": "2024-08-30 15:00"
    },
    {
      "timestamp": 1725022800,
      "price": 84.26,
      "datetime": "2024-08-30 16:00"
    },
    {
      "timestamp": 1725026400,
      "price": 105.72,
      "datetime": "2024-08-30 17:00"
    },
    {
      "timestamp": 1725030000,
      "price": 164.27,
      "datetime": "2024-08-30 18:00"
    },
    {
      "timestamp": 1725033600,
      "price": 234.23,
      "datetime": "2024-08-30 19:00"
    },
    {
      "timestamp": 1725037200,
      "price": 368.74,
      "datetime": "2024-08-30 20:00"
    },
    {
      "timestamp": 1725040800,
      "price": 200.1,
      "datetime": "2024-08-30 21:00"
    },
    {
      "timestamp": 1725044400,
      "price": 167.9,
      "datetime": "2024-08-30 22:00"
    },
    {
      "timestamp": 1725048000,
      "price": 109.62,
      "datetime": "2024-08-30 23:00"
    },
    {
      "timestamp": 1725051600,
      "price": 104.52,
      "datetime": "2024-08-31 00:00"
    },
    {
      "timestamp": 1725055200,
      "price": 109.19,
      "datetime": "2024-08-31 01:00"
    },
    {
      "timestamp": 1725058800,
      "price": 107.57,
      "datetime": "2024-08-31 02:00"
    },
    {
      "timestamp": 1725062400,
      "price": 103.14,
      "datetime": "2024-08-31 03:00"
    },
    {
      "timestamp": 1725066000,
      "price": 100.54,
      "datetime": "2024-08-31 04:00"
    },
    {
      "timestamp": 1725069600,
      "price": 98.68,
      "datetime": "2024-08-31 05:00"
    },
    {
      "timestamp": 1725073200,
      "price": 99.99,
      "datetime": "2024-08-31 06:00"
    },
    {
      "timestamp": 1725076800,
      "price": 114.54,
      "datetime": "2024-08-31 07:00"
    },
    {
      "timestamp": 1725080400,
      "price": 115.13,
      "datetime": "2024-08-31 08:00"
    },
    {
      "timestamp": 1725084000,
      "price": 111.09,
      "datetime": "2024-08-31 09:00"
    },
    {
      "timestamp": 1725087600,
      "price": 84.92,
      "datetime": "2024-08-31 10:00"
    },
    {
      "timestamp": 1725091200,
      "price": 60.13,
      "datetime": "2024-08-31 11:00"
    },
    {
      "timestamp": 1725094800,
      "price": 90.09,
      "datetime": "2024-08-31 12:00"
    },
    {
      "timestamp": 1725098400,
      "price": 107.22,
      "datetime": "2024-08-31 13:00"
    },
    {
      "timestamp": 1725102000,
      "price": 93.47,
      "datetime": "2024-08-31 14:00"
    },
    {
      "timestamp": 1725105600,
      "price": 90.08,
      "datetime": "2024-08-31 15:00"
    },
    {
      "timestamp": 1725109200,
      "price": 80.07,
      "datetime": "2024-08-31 16:00"
    },
    {
      "timestamp": 1725112800,
      "price": 82.87,
      "datetime": "2024-08-31 17:00"
    },
    {
      "timestamp": 1725116400,
      "price": 109.2,
      "datetime": "2024-08-31 18:00"
    },
    {
      "timestamp": 1725120000,
      "price": 158.24,
      "datetime": "2024-08-31 19:00"
    },
    {
      "timestamp": 1725123600,
      "price": 168.1,
      "datetime": "2024-08-31 20:00"
    },
    {
      "timestamp": 1725127200,
      "price": 156.92,
      "datetime": "2024-08-31 21:00"
    },
    {
      "timestamp": 1725130800,
      "price": 150.05,
      "datetime": "2024-08-31 22:00"
    },
    {
      "timestamp": 1725134400,
      "price": 128.98,
      "datetime": "2024-08-31 23:00"
    },
    {
      "timestamp": 1725138000,
      "price": 109.13,
      "datetime": "2024-09-01 00:00"
    },
    {
      "timestamp": 1725141600,
      "price": 98.87,
      "datetime": "2024-09-01 01:00"
    },
    {
      "timestamp": 1725145200,
      "price": 86.07,
      "datetime": "2024-09-01 02:00"
    }
  ]
}